pyoneline/__init__.py
pyoneline/transformer_utils.py
pyoneline-1.1.26.dist-info/LICENSE
pyoneline-1.1.26.dist-info/METADATA
pyoneline-1.1.26.dist-info/WHEEL
pyoneline-1.1.26.dist-info/top_level.txt
pyoneline-1.1.26.dist-info/RECORD
