Metadata-Version: 2.1
Name: pyoneline
Version: 1.1.26
Summary: I wish we can solve all questions with one-line code!
Home-page: https://github.com/StephenZMZ/OneLine.git
Author: Stephen.Z
Author-email: 15242200221@163.com
License: MIT
Keywords: python one line
Platform: UNKNOWN
Classifier: Intended Audience :: Developers
Classifier: Topic :: Software Development :: Build Tools
Classifier: License :: OSI Approved :: MIT License
Classifier: Programming Language :: Python :: 2.6
Classifier: Programming Language :: Python :: 2.7
Classifier: Programming Language :: Python :: 3
Classifier: Programming Language :: Python :: 3.3
Classifier: Programming Language :: Python :: 3.4
Classifier: Programming Language :: Python :: 3.5
